rodario/__init__.py
rodario/decorators.py
rodario/exceptions.py
rodario/future.py
rodario/registry.py
rodario/setup.py
rodario/actors/__init__.py
rodario/actors/actor.py
rodario/actors/clusterproxy.py
rodario/actors/proxy.py
rodario-1.0.0a8.dist-info/DESCRIPTION.rst
rodario-1.0.0a8.dist-info/METADATA
rodario-1.0.0a8.dist-info/RECORD
rodario-1.0.0a8.dist-info/WHEEL
rodario-1.0.0a8.dist-info/metadata.json
rodario-1.0.0a8.dist-info/top_level.txt
tests/__init__.py
tests/test_actor.py
tests/test_clusterproxy.py
tests/test_decorators.py
tests/test_proxy.py
tests/test_registry.py
